huaweicloudsdkbms/__init__.py
huaweicloudsdkbms/v1/__init__.py
huaweicloudsdkbms/v1/bms_async_client.py
huaweicloudsdkbms/v1/bms_client.py
huaweicloudsdkbms/v1/model/__init__.py
huaweicloudsdkbms/v1/model/absolute.py
huaweicloudsdkbms/v1/model/add_server_nics_req.py
huaweicloudsdkbms/v1/model/add_server_nics_request.py
huaweicloudsdkbms/v1/model/add_server_nics_response.py
huaweicloudsdkbms/v1/model/address.py
huaweicloudsdkbms/v1/model/address_info.py
huaweicloudsdkbms/v1/model/addresses.py
huaweicloudsdkbms/v1/model/asic_accelerator_info.py
huaweicloudsdkbms/v1/model/attach_baremetal_server_volume_request.py
huaweicloudsdkbms/v1/model/attach_baremetal_server_volume_response.py
huaweicloudsdkbms/v1/model/attach_volume_body.py
huaweicloudsdkbms/v1/model/available_resource_resp.py
huaweicloudsdkbms/v1/model/band_width.py
huaweicloudsdkbms/v1/model/bare_metal_modify_port_request.py
huaweicloudsdkbms/v1/model/bare_metal_modify_port_request_body.py
huaweicloudsdkbms/v1/model/baremetal_server_tag.py
huaweicloudsdkbms/v1/model/batch_create_baremetal_server_tags_request.py
huaweicloudsdkbms/v1/model/batch_create_baremetal_server_tags_request_body.py
huaweicloudsdkbms/v1/model/batch_create_baremetal_server_tags_response.py
huaweicloudsdkbms/v1/model/batch_delete_baremetal_server_tags_request.py
huaweicloudsdkbms/v1/model/batch_delete_baremetal_server_tags_request_body.py
huaweicloudsdkbms/v1/model/batch_delete_baremetal_server_tags_response.py
huaweicloudsdkbms/v1/model/batch_reboot_baremetal_servers_request.py
huaweicloudsdkbms/v1/model/batch_reboot_baremetal_servers_response.py
huaweicloudsdkbms/v1/model/batch_start_baremetal_servers_request.py
huaweicloudsdkbms/v1/model/batch_start_baremetal_servers_response.py
huaweicloudsdkbms/v1/model/batch_stop_baremetal_servers_request.py
huaweicloudsdkbms/v1/model/batch_stop_baremetal_servers_response.py
huaweicloudsdkbms/v1/model/change_baremetal_name_body.py
huaweicloudsdkbms/v1/model/change_baremetal_name_responses_servers.py
huaweicloudsdkbms-3.1.184.dist-info/METADATA
huaweicloudsdkbms-3.1.184.dist-info/WHEEL
huaweicloudsdkbms-3.1.184.dist-info/licenses/LICENSE
huaweicloudsdkbms-3.1.184.dist-info/RECORD
